lazr.jobrunner-1.1-py3.13-nspkg.pth
lazr/jobrunner/__init__.py
lazr/jobrunner/celeryconfig.py
lazr/jobrunner/celerytask.py
lazr/jobrunner/jobrunner.py
lazr/jobrunner/bin/__init__.py
lazr/jobrunner/bin/clear_queues.py
lazr/jobrunner/bin/jobrunnerctl.py
lazr/jobrunner/tests/__init__.py
lazr/jobrunner/tests/config1.py
lazr/jobrunner/tests/config_do_not_create_missing_queues.py
lazr/jobrunner/tests/config_no_prefetch.py
lazr/jobrunner/tests/config_two_queues.py
lazr/jobrunner/tests/simple_config.py
lazr/jobrunner/tests/test_celerytask.py
lazr/jobrunner/tests/test_jobrunner.py
lazr/jobrunner/tests/test_jobrunnerctl.py
lazr/jobrunner/tests/time_limit_config.py
lazr/jobrunner/tests/time_limit_config_fast_lane.py
lazr/jobrunner/tests/time_limit_config_slow_lane.py
lazr_jobrunner-1.1.dist-info/licenses/COPYING.txt
lazr_jobrunner-1.1.dist-info/METADATA
lazr_jobrunner-1.1.dist-info/WHEEL
lazr_jobrunner-1.1.dist-info/entry_points.txt
lazr_jobrunner-1.1.dist-info/namespace_packages.txt
lazr_jobrunner-1.1.dist-info/top_level.txt
lazr_jobrunner-1.1.dist-info/RECORD
