Metadata-Version: 2.4
Name: lazr.jobrunner
Version: 1.1
Summary: A Celery based job runner
Home-page: https://launchpad.net/lazr.jobrunner
Author: Launchpad Developers
Author-email: launchpad-dev@lists.launchpad.net
License: GPL v3
Requires-Python: >=3.8
License-File: COPYING.txt
Requires-Dist: celery>=5.4.0; python_version >= "3.8"
Provides-Extra: test
Requires-Dist: oops>=0.0.11; extra == "test"
Requires-Dist: six; extra == "test"
Requires-Dist: zope.testing<5.0.0; extra == "test"
Dynamic: author
Dynamic: author-email
Dynamic: description
Dynamic: home-page
Dynamic: keywords
Dynamic: license
Dynamic: license-file
Dynamic: provides-extra
Dynamic: requires-dist
Dynamic: requires-python
Dynamic: summary
